svglatex/__init__.py
svglatex/_version.py
svglatex/converter.py
svglatex/interface.py
svglatex-0.0.3.dist-info/LICENSE
svglatex-0.0.3.dist-info/METADATA
svglatex-0.0.3.dist-info/WHEEL
svglatex-0.0.3.dist-info/entry_points.txt
svglatex-0.0.3.dist-info/top_level.txt
svglatex-0.0.3.dist-info/RECORD
